[
  {"種族": "人間", "カナ": "ヒューマン", "初期人数": 50, "詳細": null},
  {"種族": "森人", "カナ": "エルフ", "初期人数": 50, "詳細": null},
  {"種族": "土人", "カナ": "ドワーフ", "初期人数": 50, "詳細": null},
  {"種族": "獣人", "カナ": "ビーストマン", "初期人数": 60, "詳細": null},
  {"種族": "竜人", "カナ": "ドラゴニュート", "初期人数": 15, "詳細": null},
  {"種族": "大鬼", "カナ": "オーガ", "初期人数": 12, "詳細": null},
  {"種族": "巨人", "カナ": "ジャイアント", "初期人数": 4, "詳細": null},
  {"種族": "鬼妖", "カナ": "ゴブリン", "初期人数": 90, "詳細": null},
  {"種族": "悪魔", "カナ": "デヴィル", "初期人数": 5, "詳細": null},
  {"種族": "天使", "カナ": "エンジェル", "初期人数": 5, "詳細": null},
  {"種族": "吸血鬼", "カナ": "ヴァンパイア", "初期人数": 3, "詳細": null}
]